{ "compressionlevel":-1,
 "height":9,
 "infinite":false,
 "layers":[
        {
         "data":[263, 312, 259, 259, 259, 259, 259, 259, 259, 259, 259, 259, 259, 312, 262,
            232, 373, 231, 373, 231, 373, 231, 373, 231, 373, 231, 373, 231, 373, 230,
            232, 231, 373, 231, 373, 231, 373, 231, 373, 231, 373, 231, 373, 231, 230,
            232, 373, 231, 373, 231, 373, 231, 373, 231, 373, 231, 373, 231, 373, 230,
            232, 231, 373, 231, 373, 231, 373, 231, 373, 231, 373, 231, 373, 231, 230,
            232, 373, 231, 373, 231, 373, 231, 373, 231, 373, 231, 373, 231, 373, 230,
            232, 231, 373, 231, 373, 231, 373, 231, 373, 231, 373, 231, 373, 231, 230,
            232, 373, 231, 373, 231, 373, 231, 373, 231, 373, 231, 373, 231, 373, 230,
            235, 203, 203, 203, 203, 203, 203, 203, 203, 203, 203, 203, 203, 203, 234],
         "height":9,
         "id":1,
         "name":"base",
         "opacity":1,
         "type":"tilelayer",
         "visible":true,
         "width":15,
         "x":0,
         "y":0
        }, 
        {
         "data":[0, 0, 0, 0, 0, 0, 0, 0, 0, 0, 0, 0, 0, 0, 0,
            0, 0, 0, 0, 0, 0, 0, 0, 0, 0, 0, 0, 0, 0, 0,
            0, 0, 0, 0, 0, 0, 0, 584, 0, 0, 0, 0, 0, 0, 0,
            0, 0, 0, 0, 0, 0, 584, 0, 584, 0, 0, 0, 0, 0, 0,
            0, 0, 0, 0, 0, 584, 0, 0, 0, 584, 0, 0, 0, 0, 0,
            0, 0, 0, 0, 584, 0, 0, 0, 0, 0, 584, 0, 0, 0, 0,
            0, 0, 0, 0, 0, 0, 0, 0, 0, 0, 0, 0, 0, 0, 0,
            0, 0, 0, 0, 0, 0, 0, 0, 0, 0, 0, 0, 0, 0, 0,
            0, 0, 0, 0, 0, 0, 0, 0, 0, 0, 0, 0, 0, 0, 0],
         "height":9,
         "id":4,
         "name":"spikes",
         "opacity":1,
         "type":"tilelayer",
         "visible":true,
         "width":15,
         "x":0,
         "y":0
        }, 
        {
         "draworder":"topdown",
         "id":3,
         "name":"enemies",
         "objects":[
                {
                 "height":0,
                 "id":1,
                 "name":"orc",
                 "point":true,
                 "rotation":0,
                 "type":"",
                 "visible":true,
                 "width":0,
                 "x":215.744268647078,
                 "y":22.3183726186632
                }, 
                {
                 "height":0,
                 "id":2,
                 "name":"orc",
                 "point":true,
                 "rotation":0,
                 "type":"",
                 "visible":true,
                 "width":0,
                 "x":23.8682596060704,
                 "y":22.0083952211818
                }],
         "opacity":1,
         "type":"objectgroup",
         "visible":true,
         "x":0,
         "y":0
        }],
 "nextlayerid":5,
 "nextobjectid":3,
 "orientation":"orthogonal",
 "renderorder":"right-down",
 "tiledversion":"1.11.2",
 "tileheight":16,
 "tilesets":[
        {
         "firstgid":1,
         "source":"base.tsx"
        }, 
        {
         "firstgid":561,
         "source":"old_base.tsx"
        }],
 "tilewidth":16,
 "type":"map",
 "version":"1.10",
 "width":15
}